LICENSE
MANIFEST.in
README.md
README.rst
requirements.txt
setup.cfg
setup.py
aws_is_instance_healthy.egg-info/PKG-INFO
aws_is_instance_healthy.egg-info/SOURCES.txt
aws_is_instance_healthy.egg-info/dependency_links.txt
aws_is_instance_healthy.egg-info/requires.txt
aws_is_instance_healthy.egg-info/top_level.txt
vivareal/__init__.py
vivareal/cli/__init__.py
vivareal/cli/am_i_healthy.py
vivareal/cli/is_instance_healthy.py