Metadata-Version: 1.0
Name: aws-is-instance-healthy
Version: 0.4.4
Summary: UNKNOWN
Home-page: http://www.vivareal.com.br/
Author: Marcos Araujo Sobrinho
Author-email: marcos.sobrinho@vivareal.com
License: MIT
Platform: UNKNOWN
